[
  {
    "type": "INT",
    "value": 4,
    "posStart": {
      "idx": 0,
      "line": 0,
      "column": 0,
      "fileName": "<Program>",
      "fileText": "4/0"
    },
    "posEnd": {
      "idx": 1,
      "line": 0,
      "column": 1,
      "fileName": "<Program>",
      "fileText": "4/0"
    }
  },
  {
    "type": "DIV",
    "posStart": {
      "idx": 1,
      "line": 0,
      "column": 1,
      "fileName": "<Program>",
      "fileText": "4/0"
    },
    "posEnd": {
      "idx": 2,
      "line": 0,
      "column": 2,
      "fileName": "<Program>",
      "fileText": "4/0"
    }
  },
  {
    "type": "INT",
    "value": 0,
    "posStart": {
      "idx": 2,
      "line": 0,
      "column": 2,
      "fileName": "<Program>",
      "fileText": "4/0"
    },
    "posEnd": {
      "idx": 3,
      "line": 0,
      "column": 3,
      "fileName": "<Program>",
      "fileText": "4/0"
    }
  },
  {
    "type": "EOF",
    "posStart": {
      "idx": 3,
      "line": 0,
      "column": 3,
      "fileName": "<Program>",
      "fileText": "4/0"
    },
    "posEnd": {
      "idx": 4,
      "line": 0,
      "column": 4,
      "fileName": "<Program>",
      "fileText": "4/0"
    }
  }
]